{
  "variants": {
    "facing=east,lit=false": {
      "model": "ttoi:block/cnfurnace",
      "y": 90
    },
    "facing=east,lit=true": {
      "model": "ttoi:block/cnfurnace_on",
      "y": 90
    },
    "facing=north,lit=false": {
      "model": "ttoi:block/cnfurnace"
    },
    "facing=north,lit=true": {
      "model": "ttoi:block/cnfurnace_on"
    },
    "facing=south,lit=false": {
      "model": "ttoi:block/cnfurnace",
      "y": 180
    },
    "facing=south,lit=true": {
      "model": "ttoi:block/cnfurnace_on",
      "y": 180
    },
    "facing=west,lit=false": {
      "model": "ttoi:block/cnfurnace",
      "y": 270
    },
    "facing=west,lit=true": {
      "model": "ttoi:block/cnfurnace_on",
      "y": 270
    }
  }
}